hed/__init__.py
hed/_version.py
hed/cli/__init__.py
hed/cli/cli.py
hed/errors/__init__.py
hed/errors/error_messages.py
hed/errors/error_reporter.py
hed/errors/error_types.py
hed/errors/exceptions.py
hed/errors/known_error_codes.py
hed/errors/schema_error_messages.py
hed/models/__init__.py
hed/models/base_input.py
hed/models/basic_search.py
hed/models/basic_search_util.py
hed/models/column_mapper.py
hed/models/column_metadata.py
hed/models/def_expand_gather.py
hed/models/definition_dict.py
hed/models/definition_entry.py
hed/models/df_util.py
hed/models/hed_group.py
hed/models/hed_string.py
hed/models/hed_tag.py
hed/models/model_constants.py
hed/models/query_expressions.py
hed/models/query_handler.py
hed/models/query_service.py
hed/models/query_util.py
hed/models/sidecar.py
hed/models/spreadsheet_input.py
hed/models/string_util.py
hed/models/tabular_input.py
hed/models/timeseries_input.py
hed/resources/word_cloud_brain_mask.png
hed/schema/__init__.py
hed/schema/hed_cache.py
hed/schema/hed_cache_lock.py
hed/schema/hed_schema.py
hed/schema/hed_schema_base.py
hed/schema/hed_schema_constants.py
hed/schema/hed_schema_entry.py
hed/schema/hed_schema_group.py
hed/schema/hed_schema_io.py
hed/schema/hed_schema_section.py
hed/schema/schema_attribute_validator_hed_id.py
hed/schema/schema_attribute_validators.py
hed/schema/schema_comparer.py
hed/schema/schema_compliance.py
hed/schema/schema_header_util.py
hed/schema/schema_validation_util.py
hed/schema/schema_validation_util_deprecated.py
hed/schema/schema_data/HED8.0.0.xml
hed/schema/schema_data/HED8.1.0.xml
hed/schema/schema_data/HED8.2.0.xml
hed/schema/schema_data/HED8.3.0.xml
hed/schema/schema_data/HED8.4.0.xml
hed/schema/schema_data/HED_lang_1.0.0.xml
hed/schema/schema_data/HED_lang_1.1.0.xml
hed/schema/schema_data/HED_score_1.0.0.xml
hed/schema/schema_data/HED_score_1.1.0.xml
hed/schema/schema_data/HED_score_2.0.0.xml
hed/schema/schema_data/HED_score_2.1.0.xml
hed/schema/schema_data/HED_testlib_1.0.2.xml
hedtools-0.8.1.dist-info/licenses/LICENSE
hedtools-0.8.1.dist-info/METADATA
hedtools-0.8.1.dist-info/WHEEL
hedtools-0.8.1.dist-info/entry_points.txt
hedtools-0.8.1.dist-info/top_level.txt
hedtools-0.8.1.dist-info/RECORD
