Metadata-Version: 2.4
Name: hedtools
Version: 0.8.1
Summary: HED validation, summary, and analysis tools for annotating events and experimental metadata.
Author: VisLab, Ian Callanan, Monique Dennisen, Jeremy Cockfield, Alexander Jones, Owen Winterberg
Author-email: Kay Robbins <Kay.Robbins@utsa.edu>
Maintainer-email: Kay Robbins <Kay.Robbins@utsa.edu>
License: MIT
Project-URL: Homepage, https://www.hedtags.org/
Project-URL: Documentation, https://www.hedtags.org/hed-python/
Project-URL: Repository, https://github.com/hed-standard/hed-python/
Project-URL: Bug Tracker, https://github.com/hed-standard/hed-python/issues
Project-URL: Changelog, https://github.com/hed-standard/hed-python/blob/main/CHANGELOG.md
Project-URL: HED Resources, https://www.hed-resources.org
Keywords: HED,hierarchical event descriptors,validation,neuroscience,BIDS,events,metadata,annotation
Classifier: Programming Language :: Python :: 3
Classifier: Programming Language :: Python :: 3.10
Classifier: Programming Language :: Python :: 3.11
Classifier: Programming Language :: Python :: 3.12
Classifier: Programming Language :: Python :: 3.13
Classifier: Programming Language :: Python :: 3.14
Classifier: Operating System :: OS Independent
Classifier: Development Status :: 5 - Production/Stable
Classifier: Intended Audience :: Developers
Classifier: Intended Audience :: Science/Research
Classifier: Topic :: Scientific/Engineering
Classifier: Topic :: Software Development :: Libraries :: Python Modules
Classifier: License :: OSI Approved :: MIT License
Requires-Python: >=3.10
License-File: LICENSE
Requires-Dist: click>=8.0.0
Requires-Dist: defusedxml
Requires-Dist: et-xmlfile
Requires-Dist: inflect
Requires-Dist: jsonschema
Requires-Dist: matplotlib>=3.9.0
Requires-Dist: numpy
Requires-Dist: openpyxl
Requires-Dist: pandas
Requires-Dist: portalocker
Requires-Dist: python-dateutil
Requires-Dist: pytz
Requires-Dist: semantic-version
Requires-Dist: six
Requires-Dist: wordcloud==1.9.4
Provides-Extra: dev
Requires-Dist: ruff>=0.8.0; extra == "dev"
Requires-Dist: codespell>=2.2.0; extra == "dev"
Requires-Dist: black>=24.0.0; extra == "dev"
Provides-Extra: docs
Requires-Dist: sphinx>=7.0.0; extra == "docs"
Requires-Dist: furo>=2023.9.10; extra == "docs"
Requires-Dist: sphinx-copybutton>=0.5.2; extra == "docs"
Requires-Dist: myst-parser>=2.0.0; extra == "docs"
Requires-Dist: sphinx-autodoc-typehints>=1.24.0; extra == "docs"
Requires-Dist: linkify-it-py>=2.0.0; extra == "docs"
Provides-Extra: test
Requires-Dist: coverage>=7.0.0; extra == "test"
Dynamic: license-file
